nexium_api/__init__.py
nexium_api/api/__init__.py
nexium_api/api/api.py
nexium_api/api_client/__init__.py
nexium_api/api_client/api_client.py
nexium_api/api_client/protocol.py
nexium_api/request/__init__.py
nexium_api/request/base_auth.py
nexium_api/request/base_data.py
nexium_api/request/process_request.py
nexium_api/request/request.py
nexium_api/response/__init__.py
nexium_api/response/base_data.py
nexium_api/response/error.py
nexium_api/response/response.py
nexium_api/response/state.py
nexium_api/router/__init__.py
nexium_api/router/base_router.py
nexium_api/router/route.py
nexium_api/utils/__init__.py
nexium_api/utils/api_error.py
nexium_api/utils/base_facade_service.py
nexium_api/utils/crypto.py
nexium_api/utils/get_ip.py
nexium_api/utils/request_context.py
nexium_api/utils/validation_error.py
nexium_api-0.5.6.dist-info/LICENSE
nexium_api-0.5.6.dist-info/METADATA
nexium_api-0.5.6.dist-info/WHEEL
nexium_api-0.5.6.dist-info/top_level.txt
nexium_api-0.5.6.dist-info/RECORD
