Metadata-Version: 2.1
Name: nexium_api
Version: 0.5.6
Summary: Standardized, simplified API development
Home-page: https://github.com/nexium-dev/nexium_api
Author: Nexium
Author-email: info@nexium.me
License: MIT
Classifier: Programming Language :: Python :: 3
Classifier: License :: OSI Approved :: MIT License
Classifier: Operating System :: OS Independent
Requires-Python: >=3.11
License-File: LICENSE
Requires-Dist: fastapi
Requires-Dist: starlette
Requires-Dist: sqlmodel
Requires-Dist: orjson
Requires-Dist: uvicorn
Requires-Dist: aiohttp
Requires-Dist: pydantic==2.10
